<?xml version="1.0" encoding="UTF-8"?>
<objInstruct>
    <ID></ID>
    <USER></USER>
    <COMPANY>Action 365 Ltd - Pukka</COMPANY>
    <SUBCOMPANY>Pukka PC</SUBCOMPANY>
    <INSPECTIONTYPE>Physical</INSPECTIONTYPE>
    <POLICYCLAIMREF>PC70181</POLICYCLAIMREF>
    <POLICYCOVER>Comprehensive</POLICYCOVER>
    <REPORTTYPE>CAR</REPORTTYPE>
    <VEHICLETYPE>INCIDENTDAMAGEASSESSMENT</VEHICLETYPE>
    <DATEOFLOSS>20190103</DATEOFLOSS>
    <ISVEHICLEMOBILE>Yes</ISVEHICLEMOBILE>
    <TYPEOFDAMAGESUSTAINED>IMPACT</TYPEOFDAMAGESUSTAINED>
    <VATREG>NO</VATREG>
    <EXCESS>99999.00</EXCESS>
    <VRM>AO56PZW</VRM>
    <VIN></VIN>
    <MAKE>PEUGEOT</MAKE>
    <MODEL>206 VERVE</MODEL>
    <YEAR>2008</YEAR>
    <CLIENTOWNREPAIRER>FALSE</CLIENTOWNREPAIRER>
    <CLAIMANT_POSTCODE>TE5 7IN</CLAIMANT_POSTCODE>
    <CLAIMANT_TYPE>Fault</CLAIMANT_TYPE>
    <CLAIMANT_NAME>Mr Lee Skinner</CLAIMANT_NAME>
    <CLAIMANT_ADDRESS1>123 Test Avenue</CLAIMANT_ADDRESS1>
    <CLAIMANT_ADDRESS2>Testville</CLAIMANT_ADDRESS2>
    <CLAIMANT_TOWN>South Testshire</CLAIMANT_TOWN>
    <CLAIMANT_TELEPHONE>07123456789</CLAIMANT_TELEPHONE>
    <CLAIMANT_MOBILE></CLAIMANT_MOBILE>
    <LOCATION_POSTCODE>TE5 7IN</LOCATION_POSTCODE>
    <LOCATION_NAME>Police Recovered</LOCATION_NAME>
    <LOCATION_ADDRESS1>123 Test Avenue</LOCATION_ADDRESS1>
    <LOCATION_ADDRESS2>Testville</LOCATION_ADDRESS2>
    <LOCATION_TOWN>South Testshire</LOCATION_TOWN>
    <LOCATION_TELEPHONE>07123456789</LOCATION_TELEPHONE>
    <SPECIALNOTES>notes notes notes</SPECIALNOTES>
</objInstruct>
